dbf_light/__init__.py
dbf_light/_base.py
dbf_light/cast.py
dbf_light/cli.py
dbf_light/definitions.py
dbf_light/exceptions.py
dbf_light/light.py
dbf_light/utils.py
dbf_light-1.0.0.dist-info/DESCRIPTION.rst
dbf_light-1.0.0.dist-info/METADATA
dbf_light-1.0.0.dist-info/RECORD
dbf_light-1.0.0.dist-info/WHEEL
dbf_light-1.0.0.dist-info/entry_points.txt
dbf_light-1.0.0.dist-info/metadata.json
dbf_light-1.0.0.dist-info/top_level.txt
