Metadata-Version: 2.1
Name: dbf-light
Version: 1.0.0
Summary: Light and easy DBF reader
Home-page: https://github.com/idlesign/dbf_light
Author: Igor `idle sign` Starikov
Author-email: idlesign@yandex.ru
License: BSD 3-Clause License
Platform: UNKNOWN
Classifier: Development Status :: 5 - Production/Stable
Classifier: Operating System :: OS Independent
Classifier: Programming Language :: Python
Classifier: Programming Language :: Python :: 2
Classifier: Programming Language :: Python :: 2.7
Classifier: Programming Language :: Python :: 3
Classifier: Programming Language :: Python :: 3.5
Classifier: Programming Language :: Python :: 3.6
Classifier: Programming Language :: Python :: 3.7
Classifier: Programming Language :: Python :: 3.8
Classifier: License :: OSI Approved :: BSD License
Provides-Extra: cli
